n7/__init__.py
n7/__main__.py
n7/commands/__init__.py
n7/commands/builders/__init__.py
n7/commands/builders/black_command_builder.py
n7/commands/builders/docker_command_builder.py
n7/commands/builders/docker_compose_command_builder.py
n7/commands/builders/mypy_command_builder.py
n7/commands/builders/pytest_command_builder.py
n7/commands/builders/ruff_command_builder.py
n7/commands/builders/tests/__init__.py
n7/commands/builders/tests/test_black_command_builder.py
n7/commands/builders/tests/test_docker_command_builder.py
n7/commands/builders/tests/test_docker_compose_command_builder.py
n7/commands/builders/tests/test_mypy_command_builder.py
n7/commands/builders/tests/test_pytest_command_builder.py
n7/commands/builders/tests/test_ruff_command_builder.py
n7/commands/docker/__init__.py
n7/commands/docker/container/__init__.py
n7/commands/docker/container/connect_postgres_command.py
n7/commands/docker/container/connect_shell_command.py
n7/commands/docker/container/down_command.py
n7/commands/docker/container/logs_command.py
n7/commands/docker/container/py_manage_command.py
n7/commands/docker/container/up_command.py
n7/commands/docker/container/tests/__init__.py
n7/commands/docker/container/tests/test_connect_postgres_command.py
n7/commands/docker/container/tests/test_connect_shell_command.py
n7/commands/docker/container/tests/test_down_command.py
n7/commands/docker/container/tests/test_logs_command.py
n7/commands/docker/container/tests/test_py_manage_command.py
n7/commands/docker/container/tests/test_up_command.py
n7/commands/docker/format/__init__.py
n7/commands/docker/format/docker_black_command.py
n7/commands/docker/format/docker_mypy_command.py
n7/commands/docker/format/docker_pycheck_command.py
n7/commands/docker/format/docker_pyqa_command.py
n7/commands/docker/format/docker_ruff_command.py
n7/commands/docker/format/docker_uv_command.py
n7/commands/docker/format/tests/test_docker_black_command.py
n7/commands/docker/format/tests/test_docker_mypy_command.py
n7-1.7.0.dist-info/licenses/LICENSE
n7-1.7.0.dist-info/METADATA
n7-1.7.0.dist-info/WHEEL
n7-1.7.0.dist-info/entry_points.txt
n7-1.7.0.dist-info/top_level.txt
n7-1.7.0.dist-info/RECORD
