Metadata-Version: 2.4
Name: n7
Version: 1.7.0
Summary: CLI global pour les projets N7
Author: nseven
License: MIT
Requires-Python: >=3.13
License-File: LICENSE
Requires-Dist: typer
Requires-Dist: pyyaml
Dynamic: license-file
